{
  "symbol": "BTC",
  "timestamp": "2025-11-01T12:02:00.945103",
  "spot_price": 110173.0,
  "overall_max_pain": 112829.81299726131,
  "expirations": {
    "2025-10-29": {
      "max_pain": 119000.0,
      "spot_price": 110173.0,
      "distance_pct": 8.011944850371687,
      "direction": "\u2191",
      "dte": 1,
      "total_oi": 194.08,
      "call_oi": 193.88,
      "put_oi": 0.19999999999999998,
      "put_call_ratio": 0.0010315659170621002
    },
    "2025-10-31": {
      "max_pain": 113000.0,
      "spot_price": 110173.0,
      "distance_pct": 2.5659644377479056,
      "direction": "\u2191",
      "dte": 1,
      "total_oi": 693169.3699999999,
      "call_oi": 410105.80999999994,
      "put_oi": 283063.56,
      "put_call_ratio": 0.6902207993590728
    },
    "2025-11-14": {
      "max_pain": 112000.0,
      "spot_price": 110173.0,
      "distance_pct": 1.6583010356439418,
      "direction": "\u2191",
      "dte": 12,
      "total_oi": 268536.52,
      "call_oi": 132878.06000000003,
      "put_oi": 135658.46,
      "put_call_ratio": 1.0209244475724584
    },
    "2025-11-21": {
      "max_pain": 110000.0,
      "spot_price": 110173.0,
      "distance_pct": 0.15702576856398573,
      "direction": "\u2193",
      "dte": 19,
      "total_oi": 14446.7,
      "call_oi": 7896.280000000001,
      "put_oi": 6550.42,
      "put_call_ratio": 0.8295577157851545
    },
    "2025-11-28": {
      "max_pain": 113000.0,
      "spot_price": 110173.0,
      "distance_pct": 2.5659644377479056,
      "direction": "\u2191",
      "dte": 26,
      "total_oi": 849363.49,
      "call_oi": 492776.59,
      "put_oi": 356586.9,
      "put_call_ratio": 0.7236279223410349
    }
  }
}