{
  "symbol": "BTC",
  "timestamp": "2025-11-02T22:02:53.201631",
  "spot_price": 110301.7,
  "overall_max_pain": 112549.16339947622,
  "expirations": {
    "2025-10-29": {
      "max_pain": 119000.0,
      "spot_price": 110301.7,
      "distance_pct": 7.885916536191195,
      "direction": "\u2191",
      "dte": 1,
      "total_oi": 194.08,
      "call_oi": 193.88,
      "put_oi": 0.19999999999999998,
      "put_call_ratio": 0.0010315659170621002
    },
    "2025-10-31": {
      "max_pain": 113000.0,
      "spot_price": 110301.7,
      "distance_pct": 2.4462904923496223,
      "direction": "\u2191",
      "dte": 1,
      "total_oi": 693169.3699999999,
      "call_oi": 410105.80999999994,
      "put_oi": 283063.56,
      "put_call_ratio": 0.6902207993590728
    },
    "2025-11-14": {
      "max_pain": 111000.0,
      "spot_price": 110301.7,
      "distance_pct": 0.6330818110690977,
      "direction": "\u2191",
      "dte": 11,
      "total_oi": 496870.9600000001,
      "call_oi": 258315.02,
      "put_oi": 238555.94000000003,
      "put_call_ratio": 0.9235078161540898
    },
    "2025-11-21": {
      "max_pain": 110000.0,
      "spot_price": 110301.7,
      "distance_pct": 0.27352252957116446,
      "direction": "\u2193",
      "dte": 18,
      "total_oi": 45719.95,
      "call_oi": 26993.15,
      "put_oi": 18726.8,
      "put_call_ratio": 0.6937611949698349
    },
    "2025-11-28": {
      "max_pain": 113000.0,
      "spot_price": 110301.7,
      "distance_pct": 2.4462904923496223,
      "direction": "\u2191",
      "dte": 25,
      "total_oi": 1269914.2600000002,
      "call_oi": 729554.8500000001,
      "put_oi": 540359.41,
      "put_call_ratio": 0.7406700263866384
    }
  }
}