{
  "symbol": "XRP",
  "timestamp": "2025-11-02T20:33:24.443549",
  "spot_price": 2.4984,
  "overall_max_pain": 2.6381162372192835,
  "expirations": {
    "2025-10-29": {
      "max_pain": 2.65,
      "spot_price": 2.4984,
      "distance_pct": 6.067883445405048,
      "direction": "\u2191",
      "dte": 1,
      "total_oi": 3338430.0,
      "call_oi": 592400.0,
      "put_oi": 2746030.0,
      "put_call_ratio": 4.635432140445645
    },
    "2025-10-30": {
      "max_pain": 2.65,
      "spot_price": 2.4984,
      "distance_pct": 6.067883445405048,
      "direction": "\u2191",
      "dte": 1,
      "total_oi": 524570.0,
      "call_oi": 369760.0,
      "put_oi": 154810.0,
      "put_call_ratio": 0.4186769796624838
    },
    "2025-10-31": {
      "max_pain": 2.55,
      "spot_price": 2.4984,
      "distance_pct": 2.0653218059557976,
      "direction": "\u2191",
      "dte": 1,
      "total_oi": 27249490.0,
      "call_oi": 9699060.0,
      "put_oi": 17550430.0,
      "put_call_ratio": 1.8094980338300826
    },
    "2025-11-14": {
      "max_pain": 2.65,
      "spot_price": 2.4984,
      "distance_pct": 6.067883445405048,
      "direction": "\u2191",
      "dte": 11,
      "total_oi": 258650870.0,
      "call_oi": 177541260.0,
      "put_oi": 81109610.0,
      "put_call_ratio": 0.45684935434163304
    },
    "2025-11-21": {
      "max_pain": 2.4,
      "spot_price": 2.4984,
      "distance_pct": 3.9385206532180703,
      "direction": "\u2193",
      "dte": 18,
      "total_oi": 3017560.0,
      "call_oi": 1154860.0,
      "put_oi": 1862700.0,
      "put_call_ratio": 1.6129227785186082
    }
  }
}