{
  "asset": "DOGE",
  "timestamp": "2025-11-04T22:35:13.462901",
  "spot_price": 0.18,
  "total_vanna": 9007550.47,
  "vanna_by_strike": {
    "0.14": -972872.98,
    "0.15": 0.0,
    "0.16": -440846.54,
    "0.164": 3612.33,
    "0.168": 7092.43,
    "0.17": -3860664.6,
    "0.176": 3463.42,
    "0.18": 152814.05,
    "0.185": -2037.43,
    "0.19": 2639406.63,
    "0.2": 3871794.3,
    "0.21": 2648073.65,
    "0.22": 1715365.18,
    "0.23": 18916.02,
    "0.24": 2378331.47,
    "0.25": 726753.84,
    "0.26": 118348.71
  },
  "top_vanna_strikes": [
    [
      0.2,
      3871794.3
    ],
    [
      0.17,
      -3860664.6
    ],
    [
      0.21,
      2648073.65
    ],
    [
      0.19,
      2639406.63
    ],
    [
      0.24,
      2378331.47
    ]
  ],
  "interpretation": "BULLISH_STRONG"
}