{
  "asset": "MNT",
  "timestamp": "2025-11-04T22:05:09.246264",
  "spot_price": 1.43,
  "total_vanna": 6030214.34,
  "vanna_by_strike": {
    "0.9": 439.9,
    "1.05": 38.3,
    "1.1": 1039570.87,
    "1.15": 1560.95,
    "1.2": -11780.75,
    "1.24": -995.67,
    "1.25": 17661.22,
    "1.3": 32894.55,
    "1.35": 114.11,
    "1.4": 24896.06,
    "1.45": 15098.9,
    "1.5": 12210.23,
    "1.55": 270416.75,
    "1.58": 438402.38,
    "1.6": 418455.8,
    "1.62": 58073.52,
    "1.64": 0.0,
    "1.66": 69.63,
    "1.68": 989.46,
    "1.89": 882508.48,
    "1.9": 0.0,
    "1.92": 1143576.67,
    "1.98": 1217258.89,
    "1.99": 3734.75,
    "2.0": 465019.32
  },
  "top_vanna_strikes": [
    [
      1.98,
      1217258.89
    ],
    [
      1.92,
      1143576.67
    ],
    [
      1.1,
      1039570.87
    ],
    [
      1.89,
      882508.48
    ],
    [
      2.0,
      465019.32
    ]
  ],
  "interpretation": "BULLISH_STRONG"
}